1d9aa09f89826af56348__mypyc.cpython-311-darwin.so
untruncate_json-1.1.0.dist-info/RECORD
untruncate_json-1.1.0.dist-info/LICENSE
untruncate_json-1.1.0.dist-info/WHEEL
untruncate_json-1.1.0.dist-info/entry_points.txt
untruncate_json-1.1.0.dist-info/top_level.txt
untruncate_json-1.1.0.dist-info/METADATA
tests/test_basic.py
tests/__init__.py
tests/test_from_untruncate.py
untruncate_json/version.py
untruncate_json/__main__.cpython-311-darwin.so
untruncate_json/__init__.py
untruncate_json/version.cpython-311-darwin.so
untruncate_json/untrunc.cpython-311-darwin.so
untruncate_json/py.typed
untruncate_json/__init__.cpython-311-darwin.so
untruncate_json/untrunc.py
untruncate_json/__main__.py
