Metadata-Version: 2.1
Name: untruncate_json
Version: 1.1.0
Summary: Cleans up truncated json files.
Home-page: https://github.com/matthewdeanmartin/untruncate_json/
Author: Matthew Martin
Author-email: matthewdeanmartin@gmail.com
License: MIT
Project-URL: Documentation, https://github.com/matthewdeanmartin/untruncate_json
Project-URL: Repository, https://github.com/matthewdeanmartin/untruncate_json
Classifier: Development Status :: 5 - Production/Stable
Classifier: Environment :: Console
Classifier: Intended Audience :: Developers
Classifier: License :: OSI Approved :: MIT License
Classifier: Programming Language :: Python :: 3
Classifier: Programming Language :: Python :: 3.8
Classifier: Programming Language :: Python :: 3.9
Classifier: Programming Language :: Python :: 3.10
Classifier: Programming Language :: Python :: 3.11
Classifier: Programming Language :: Python :: 3.12
Classifier: Programming Language :: Python :: 3.13
Classifier: Topic :: Software Development
Classifier: Typing :: Typed
Requires-Python: >=3.8
License-File: LICENSE
